config_io/__init__.py
config_io/config.py
config_io/io.py
config_io-0.4.0.dist-info/LICENSE
config_io-0.4.0.dist-info/METADATA
config_io-0.4.0.dist-info/WHEEL
config_io-0.4.0.dist-info/top_level.txt
config_io-0.4.0.dist-info/RECORD
