Metadata-Version: 2.1
Name: config-io
Version: 0.4.0
Summary: Advanced config reading/writing/parsing for yaml/json configs.
Home-page: https://github.com/fjxmlzn/config_io
Author: Zinan Lin
Author-email: linzinan1995@gmail.com
License: MIT License
Keywords: config yaml json python addict
Platform: Any
Classifier: Programming Language :: Python
Classifier: Programming Language :: Python :: 3.6
Classifier: Programming Language :: Python :: 3.7
Classifier: Programming Language :: Python :: 3.8
Classifier: Programming Language :: Python :: 3.9
Classifier: Programming Language :: Python :: 3.10
Classifier: License :: OSI Approved :: MIT License
Classifier: Operating System :: OS Independent
Classifier: Intended Audience :: Developers
Classifier: Intended Audience :: Science/Research
Classifier: Topic :: Software Development :: Libraries :: Python Modules
License-File: LICENSE
Requires-Dist: addict
Requires-Dist: pyyaml
